<annotation>
	<folder>JPEGImages</folder>
	<filename>000591.jpg</filename>
	<path>/home/smallchild/data/VOCdevkit/qixiadataset/JPEGImages/000591.jpg</path>
	<source>
		<database>Unknown</database>
	</source>
	<size>
		<width>1280</width>
		<height>720</height>
		<depth>3</depth>
	</size>
	<segmented>0</segmented>
	<object>
		<name>chair</name>
		<pose>Unspecified</pose>
		<truncated>0</truncated>
		<difficult>0</difficult>
		<bndbox>
			<xmin>171</xmin>
			<ymin>381</ymin>
			<xmax>389</xmax>
			<ymax>573</ymax>
		</bndbox>
	</object>
	<object>
		<name>chair</name>
		<pose>Unspecified</pose>
		<truncated>0</truncated>
		<difficult>0</difficult>
		<bndbox>
			<xmin>758</xmin>
			<ymin>471</ymin>
			<xmax>1036</xmax>
			<ymax>714</ymax>
		</bndbox>
	</object>
	<object>
		<name>person</name>
		<pose>Unspecified</pose>
		<truncated>0</truncated>
		<difficult>0</difficult>
		<bndbox>
			<xmin>348</xmin>
			<ymin>186</ymin>
			<xmax>444</xmax>
			<ymax>316</ymax>
		</bndbox>
	</object>
	<object>
		<name>billboard</name>
		<pose>Unspecified</pose>
		<truncated>0</truncated>
		<difficult>0</difficult>
		<bndbox>
			<xmin>1102</xmin>
			<ymin>263</ymin>
			<xmax>1175</xmax>
			<ymax>382</ymax>
		</bndbox>
	</object>
	<object>
		<name>billboard</name>
		<pose>Unspecified</pose>
		<truncated>0</truncated>
		<difficult>0</difficult>
		<bndbox>
			<xmin>1202</xmin>
			<ymin>293</ymin>
			<xmax>1268</xmax>
			<ymax>394</ymax>
		</bndbox>
	</object>
	<object>
		<name>billboard</name>
		<pose>Unspecified</pose>
		<truncated>0</truncated>
		<difficult>0</difficult>
		<bndbox>
			<xmin>982</xmin>
			<ymin>383</ymin>
			<xmax>1058</xmax>
			<ymax>436</ymax>
		</bndbox>
	</object>
	<object>
		<name>pot</name>
		<pose>Unspecified</pose>
		<truncated>0</truncated>
		<difficult>0</difficult>
		<bndbox>
			<xmin>804</xmin>
			<ymin>337</ymin>
			<xmax>881</xmax>
			<ymax>412</ymax>
		</bndbox>
	</object>
	<object>
		<name>pot</name>
		<pose>Unspecified</pose>
		<truncated>0</truncated>
		<difficult>0</difficult>
		<bndbox>
			<xmin>121</xmin>
			<ymin>232</ymin>
			<xmax>180</xmax>
			<ymax>297</ymax>
		</bndbox>
	</object>
	<object>
		<name>billboard</name>
		<pose>Unspecified</pose>
		<truncated>0</truncated>
		<difficult>0</difficult>
		<bndbox>
			<xmin>204</xmin>
			<ymin>247</ymin>
			<xmax>240</xmax>
			<ymax>300</ymax>
		</bndbox>
	</object>
</annotation>
