<annotation>
	<folder>JPEGImages</folder>
	<filename>000915.jpg</filename>
	<path>/home/smallchild/data/VOCdevkit/qixiadataset/JPEGImages/000915.jpg</path>
	<source>
		<database>Unknown</database>
	</source>
	<size>
		<width>1280</width>
		<height>720</height>
		<depth>3</depth>
	</size>
	<segmented>0</segmented>
	<object>
		<name>chair</name>
		<pose>Unspecified</pose>
		<truncated>0</truncated>
		<difficult>0</difficult>
		<bndbox>
			<xmin>140</xmin>
			<ymin>384</ymin>
			<xmax>360</xmax>
			<ymax>567</ymax>
		</bndbox>
	</object>
	<object>
		<name>chair</name>
		<pose>Unspecified</pose>
		<truncated>0</truncated>
		<difficult>0</difficult>
		<bndbox>
			<xmin>818</xmin>
			<ymin>458</ymin>
			<xmax>1042</xmax>
			<ymax>686</ymax>
		</bndbox>
	</object>
	<object>
		<name>billboard</name>
		<pose>Unspecified</pose>
		<truncated>0</truncated>
		<difficult>0</difficult>
		<bndbox>
			<xmin>1123</xmin>
			<ymin>267</ymin>
			<xmax>1184</xmax>
			<ymax>372</ymax>
		</bndbox>
	</object>
	<object>
		<name>billboard</name>
		<pose>Unspecified</pose>
		<truncated>0</truncated>
		<difficult>0</difficult>
		<bndbox>
			<xmin>1209</xmin>
			<ymin>281</ymin>
			<xmax>1277</xmax>
			<ymax>396</ymax>
		</bndbox>
	</object>
	<object>
		<name>billboard</name>
		<pose>Unspecified</pose>
		<truncated>0</truncated>
		<difficult>0</difficult>
		<bndbox>
			<xmin>984</xmin>
			<ymin>389</ymin>
			<xmax>1055</xmax>
			<ymax>434</ymax>
		</bndbox>
	</object>
	<object>
		<name>pot</name>
		<pose>Unspecified</pose>
		<truncated>0</truncated>
		<difficult>0</difficult>
		<bndbox>
			<xmin>790</xmin>
			<ymin>324</ymin>
			<xmax>877</xmax>
			<ymax>401</ymax>
		</bndbox>
	</object>
	<object>
		<name>monitor</name>
		<pose>Unspecified</pose>
		<truncated>0</truncated>
		<difficult>0</difficult>
		<bndbox>
			<xmin>471</xmin>
			<ymin>270</ymin>
			<xmax>515</xmax>
			<ymax>356</ymax>
		</bndbox>
	</object>
	<object>
		<name>billboard</name>
		<pose>Unspecified</pose>
		<truncated>0</truncated>
		<difficult>0</difficult>
		<bndbox>
			<xmin>175</xmin>
			<ymin>243</ymin>
			<xmax>227</xmax>
			<ymax>296</ymax>
		</bndbox>
	</object>
	<object>
		<name>pot</name>
		<pose>Unspecified</pose>
		<truncated>0</truncated>
		<difficult>0</difficult>
		<bndbox>
			<xmin>111</xmin>
			<ymin>243</ymin>
			<xmax>156</xmax>
			<ymax>291</ymax>
		</bndbox>
	</object>
</annotation>
