<annotation>
	<folder>JPEGImages</folder>
	<filename>001010.jpg</filename>
	<path>/home/smallchild/data/VOCdevkit/qixiadataset/JPEGImages/001010.jpg</path>
	<source>
		<database>Unknown</database>
	</source>
	<size>
		<width>1280</width>
		<height>720</height>
		<depth>3</depth>
	</size>
	<segmented>0</segmented>
	<object>
		<name>person</name>
		<pose>Unspecified</pose>
		<truncated>0</truncated>
		<difficult>0</difficult>
		<bndbox>
			<xmin>202</xmin>
			<ymin>161</ymin>
			<xmax>372</xmax>
			<ymax>529</ymax>
		</bndbox>
	</object>
	<object>
		<name>desk</name>
		<pose>Unspecified</pose>
		<truncated>0</truncated>
		<difficult>0</difficult>
		<bndbox>
			<xmin>623</xmin>
			<ymin>355</ymin>
			<xmax>789</xmax>
			<ymax>675</ymax>
		</bndbox>
	</object>
	<object>
		<name>billboard</name>
		<pose>Unspecified</pose>
		<truncated>0</truncated>
		<difficult>0</difficult>
		<bndbox>
			<xmin>839</xmin>
			<ymin>452</ymin>
			<xmax>1067</xmax>
			<ymax>666</ymax>
		</bndbox>
	</object>
</annotation>
