<annotation>
	<folder>JPEGImages</folder>
	<filename>001162.jpg</filename>
	<path>/home/smallchild/data/VOCdevkit/qixiadataset/JPEGImages/001162.jpg</path>
	<source>
		<database>Unknown</database>
	</source>
	<size>
		<width>1280</width>
		<height>720</height>
		<depth>3</depth>
	</size>
	<segmented>0</segmented>
	<object>
		<name>person</name>
		<pose>Unspecified</pose>
		<truncated>1</truncated>
		<difficult>0</difficult>
		<bndbox>
			<xmin>253</xmin>
			<ymin>50</ymin>
			<xmax>621</xmax>
			<ymax>720</ymax>
		</bndbox>
	</object>
	<object>
		<name>person</name>
		<pose>Unspecified</pose>
		<truncated>0</truncated>
		<difficult>0</difficult>
		<bndbox>
			<xmin>805</xmin>
			<ymin>311</ymin>
			<xmax>940</xmax>
			<ymax>502</ymax>
		</bndbox>
	</object>
	<object>
		<name>chair</name>
		<pose>Unspecified</pose>
		<truncated>0</truncated>
		<difficult>0</difficult>
		<bndbox>
			<xmin>745</xmin>
			<ymin>354</ymin>
			<xmax>801</xmax>
			<ymax>476</ymax>
		</bndbox>
	</object>
	<object>
		<name>pot</name>
		<pose>Unspecified</pose>
		<truncated>0</truncated>
		<difficult>0</difficult>
		<bndbox>
			<xmin>936</xmin>
			<ymin>455</ymin>
			<xmax>1013</xmax>
			<ymax>624</ymax>
		</bndbox>
	</object>
	<object>
		<name>pot</name>
		<pose>Unspecified</pose>
		<truncated>0</truncated>
		<difficult>0</difficult>
		<bndbox>
			<xmin>1019</xmin>
			<ymin>484</ymin>
			<xmax>1076</xmax>
			<ymax>662</ymax>
		</bndbox>
	</object>
	<object>
		<name>pot</name>
		<pose>Unspecified</pose>
		<truncated>0</truncated>
		<difficult>0</difficult>
		<bndbox>
			<xmin>1086</xmin>
			<ymin>492</ymin>
			<xmax>1182</xmax>
			<ymax>691</ymax>
		</bndbox>
	</object>
</annotation>
